iotbmn/__init__.py
iotbmn/iotbmn.py
IoTBMN-0.2.5.dist-info/METADATA
IoTBMN-0.2.5.dist-info/WHEEL
IoTBMN-0.2.5.dist-info/top_level.txt
IoTBMN-0.2.5.dist-info/RECORD
